mysql_redis_cache/__init__.py
mysql_redis_cache/client.py
mysql_redis_cache/py.typed
mysql_redis_cache/server.py
actvalue_mysql_redis_cache-0.2.0.dist-info/METADATA
actvalue_mysql_redis_cache-0.2.0.dist-info/WHEEL
actvalue_mysql_redis_cache-0.2.0.dist-info/RECORD
