Metadata-Version: 2.4
Name: actvalue.mysql-redis-cache
Version: 0.2.0
Summary: Async wrapper for MySQL queries with Redis caching
Project-URL: Homepage, https://github.com/yourusername/mysql-redis-cache
Project-URL: Repository, https://github.com/yourusername/mysql-redis-cache
Project-URL: Issues, https://github.com/yourusername/mysql-redis-cache/issues
Author-email: ActValue <your-email@example.com>
License: MIT
Keywords: async,cache,database,mysql,redis
Classifier: Development Status :: 4 - Beta
Classifier: Intended Audience :: Developers
Classifier: License :: OSI Approved :: MIT License
Classifier: Programming Language :: Python :: 3
Classifier: Programming Language :: Python :: 3.13
Classifier: Topic :: Database
Classifier: Topic :: Software Development :: Libraries :: Python Modules
Requires-Python: >=3.13
Requires-Dist: aiomysql>=0.3.2
Requires-Dist: redis>=7.1.0
Provides-Extra: dev
Requires-Dist: mypy>=1.8.0; extra == 'dev'
Requires-Dist: pytest-asyncio>=0.23.0; extra == 'dev'
Requires-Dist: pytest-cov>=4.1.0; extra == 'dev'
Requires-Dist: pytest>=8.0.0; extra == 'dev'
Requires-Dist: ruff>=0.7.0; extra == 'dev'
